retry/__init__.py
retry/api.py
retry/compat.py
retry2-0.9.4.dist-info/AUTHORS
retry2-0.9.4.dist-info/LICENSE
retry2-0.9.4.dist-info/METADATA
retry2-0.9.4.dist-info/WHEEL
retry2-0.9.4.dist-info/pbr.json
retry2-0.9.4.dist-info/top_level.txt
retry2-0.9.4.dist-info/RECORD
